README.rst
setup.cfg
setup.py
src/typped/__init__.py
src/typped/builtin_parse_methods.py
src/typped/cython_shadow.py
src/typped/ebnf_classes_and_operators.py
src/typped/helpers.py
src/typped/lexer.py
src/typped/matcher.py
src/typped/pratt_constructs.py
src/typped/pratt_parser.py
src/typped/pratt_types.py
src/typped/predefined_token_sets.py
src/typped/register_grammar_with_parser.py
src/typped/shared_settings_and_exceptions.py
src/typped/text_stream.py
src/typped.egg-info/PKG-INFO
src/typped.egg-info/SOURCES.txt
src/typped.egg-info/dependency_links.txt
src/typped.egg-info/not-zip-safe
src/typped.egg-info/requires.txt
src/typped.egg-info/top_level.txt
src/typped/cython_c_code/__init__.py
src/typped/cython_c_code/src/__init__.py
src/typped/cython_c_code/src/typped/__init__.c
src/typped/cython_c_code/src/typped/__init__.py
src/typped/cython_c_code/src/typped/builtin_parse_methods.c
src/typped/cython_c_code/src/typped/ebnf_classes_and_operators.c
src/typped/cython_c_code/src/typped/helpers.c
src/typped/cython_c_code/src/typped/lexer.c
src/typped/cython_c_code/src/typped/matcher.c
src/typped/cython_c_code/src/typped/pratt_constructs.c
src/typped/cython_c_code/src/typped/pratt_parser.c
src/typped/cython_c_code/src/typped/pratt_types.c
src/typped/cython_c_code/src/typped/predefined_token_sets.c
src/typped/cython_c_code/src/typped/register_grammar_with_parser.c
src/typped/cython_c_code/src/typped/shared_settings_and_exceptions.c
src/typped/cython_c_code/src/typped/text_stream.c
test/test_basic_usage_section_examples.py
test/test_ebnf_classes_and_operators.py
test/test_example_calculator.py
test/test_example_calculator_identifier_keyed_on_values.py
test/test_example_expression_grammar.py
test/test_lexer.py
test/test_matcher.py
test/test_parser_called_from_parser.py
test/test_pratt_parser.py
test/test_pratt_types.py
test/test_simple_query_grammar.py